{
  "typeName": "AWS::Kendra::DataSource",
  "description": "Kendra DataSource",
  "sourceUrl": "https://docs.aws.amazon.com/kendra/latest/dg/hiw-data-source.html",
  "definitions": {
    "IndexId": {
      "description": "ID of Index",
      "type": "string",
      "minLength": 36,
      "maxLength": 36,
      "pattern": "[a-zA-Z0-9][a-zA-Z0-9-]*"
    },
    "Tag": {
      "description": "Tag type",
      "type": "object",
      "properties": {
        "Key": {
          "description": "A string used to identify this tag. You can specify a maximum of 128 characters for a tag key.",
          "type": "string",
          "minLength": 1,
          "maxLength": 128
        },
        "Value": {
          "description": "A string containing the value for this tag. You can specify a maximum of 256 characters for a tag value.",
          "type": "string",
          "minLength": 0,
          "maxLength": 256
        }
      },
      "required": [
        "Key",
        "Value"
      ],
      "additionalProperties": false
    },
    "DataSourceInclusionsExclusionsStrings": {
      "type": "array",
      "uniqueItems": true,
      "insertionOrder": false,
      "maxItems": 100,
      "items": {
        "type": "string",
        "minLength": 1,
        "maxLength": 50
      }
    },
    "S3Path": {
      "type": "object",
      "properties": {
        "Bucket": {
          "$ref": "#/definitions/S3BucketName"
        },
        "Key": {
          "$ref": "#/definitions/S3ObjectKey"
        }
      },
      "required": [
        "Bucket",
        "Key"
      ]
    },
    "S3BucketName": {
      "type": "string",
      "minLength": 3,
      "maxLength": 63,
      "pattern": "[a-z0-9][\\.\\-a-z0-9]{1,61}[a-z0-9]"
    },
    "S3ObjectKey": {
      "type": "string",
      "minLength": 1,
      "maxLength": 1024
    },
    "DocumentsMetadataConfiguration": {
      "type": "object",
      "properties": {
        "S3Prefix": {
          "$ref": "#/definitions/S3ObjectKey"
        }
      }
    },
    "AccessControlListConfiguration": {
      "type": "object",
      "properties": {
        "KeyPath": {
          "$ref": "#/definitions/S3ObjectKey"
        }
      }
    },
    "S3DataSourceConfiguration": {
      "description": "S3 Data Source configuration",
      "type": "object",
      "properties": {
        "BucketName": {
          "$ref": "#/definitions/S3BucketName"
        },
        "InclusionPrefixes": {
          "$ref": "#/definitions/DataSourceInclusionsExclusionsStrings"
        },
        "InclusionPatterns": {
          "$ref": "#/definitions/DataSourceInclusionsExclusionsStrings"
        },
        "ExclusionPatterns": {
          "$ref": "#/definitions/DataSourceInclusionsExclusionsStrings"
        },
        "DocumentsMetadataConfiguration": {
          "$ref": "#/definitions/DocumentsMetadataConfiguration"
        },
        "AccessControlListConfiguration": {
          "$ref": "#/definitions/AccessControlListConfiguration"
        }
      },
      "required": [
        "BucketName"
      ]
    }
  },
  "properties": {
    "Id": {
      "description": "ID of Data Source",
      "type": "string",
      "minLength": 1,
      "maxLength": 100,
      "pattern": "[a-zA-Z0-9][a-zA-Z0-9_-]*"
    },
    "Name": {
      "description": "Name of Data Source",
      "type": "string",
      "minLength": 1,
      "maxLength": 1000,
      "pattern": "[a-zA-Z0-9][a-zA-Z0-9_-]*"
    },
    "IndexId": {
      "$ref": "#/definitions/IndexId"
    },
    "Type": {
      "description": "Data Source type",
      "type": "string",
      "enum": [
        "S3"
      ]
    },
    "DataSourceConfiguration": {
      "type": "object",
      "properties": {
        "S3Configuration": {
          "$ref": "#/definitions/S3DataSourceConfiguration"
        }
      }
    },
    "Description": {
      "description": "Description of Data Source",
      "type": "string",
      "minLength": 1,
      "maxLength": 1000,
      "pattern": "^\\P{C}*$"
    },
    "Schedule": {
      "description": "Schedule",
      "type": "string"
    },
    "RoleArn": {
      "description": "Role ARN",
      "type": "string",
      "minLength": 1,
      "maxLength": 1284,
      "pattern": "arn:[a-z0-9-\\.]{1,63}:[a-z0-9-\\.]{0,63}:[a-z0-9-\\.]{0,63}:[a-z0-9-\\.]{0,63}:[^/].{0,1023}"
    },
    "Tags": {
      "description": "Tags for Data Source.",
      "type": "array",
      "uniqueItems": true,
      "insertionOrder": false,
      "maxItems": 200,
      "items": {
        "$ref": "#/definitions/Tag"
      }
    }
  },
  "required": [
    "Name",
    "IndexId",
    "Type",
    "Configuration",
    "RoleArn"
  ],
  "handlers": {
    "create": {
      "permissions": [
        "kendra:CreateDataSource"
      ]
    }
  },
  "additionalProperties": false,
  "primaryIdentifier": [
    "/properties/Id"
  ],
  "readOnlyProperties": [
    "/properties/Id"
  ],
  "createOnlyProperties": [
    "/properties/Tags",
    "/properties/Type"
  ]
}
